dcdc/__init__.py
dcdc/_version.py
dcdc/application.py
dcdc/py.typed
docker_container_domain_connector-0.1.1.dist-info/licenses/LICENCE
docker_container_domain_connector-0.1.1.dist-info/METADATA
docker_container_domain_connector-0.1.1.dist-info/WHEEL
docker_container_domain_connector-0.1.1.dist-info/entry_points.txt
docker_container_domain_connector-0.1.1.dist-info/top_level.txt
docker_container_domain_connector-0.1.1.dist-info/RECORD
