Metadata-Version: 2.4
Name: docker-container-domain-connector
Version: 0.1.1
Summary: Local DNS server for exposing docker containers on bridge networks
Author-email: Nicholas Hairs <info+dcdc@nicholashairs.com>
License: MIT License
Project-URL: GitHub, https://github.com/nhairs/docker-container-domain-connector
Classifier: Development Status :: 3 - Alpha
Classifier: Intended Audience :: Developers
Classifier: Intended Audience :: Information Technology
Classifier: Intended Audience :: System Administrators
Classifier: License :: OSI Approved :: MIT License
Classifier: Operating System :: POSIX :: Linux
Classifier: Programming Language :: Python :: 3 :: Only
Classifier: Programming Language :: Python :: 3.8
Classifier: Programming Language :: Python :: 3.9
Classifier: Programming Language :: Python :: 3.10
Classifier: Programming Language :: Python :: 3.11
Classifier: Programming Language :: Python :: 3.12
Classifier: Topic :: Internet :: Name Service (DNS)
Classifier: Topic :: System :: Networking
Classifier: Typing :: Typed
Requires-Python: >=3.8
License-File: LICENCE
Requires-Dist: docker
Requires-Dist: ifaddr
Requires-Dist: nserver
Requires-Dist: pillar
Provides-Extra: dev
Requires-Dist: types-docker; extra == "dev"
Requires-Dist: validate-pyproject[all]; extra == "dev"
Requires-Dist: black; extra == "dev"
Requires-Dist: pylint; extra == "dev"
Requires-Dist: mypy; extra == "dev"
Requires-Dist: pytest; extra == "dev"
Requires-Dist: build; extra == "dev"
Requires-Dist: setuptools; extra == "dev"
Requires-Dist: setuptools_scm; extra == "dev"
Dynamic: license-file
